bcd/bcd_up_and_down_counter.v
module bcd(up_down, clk, reset, count);
    input up_down;
    input clk, reset;
    output reg [3:0] count;

    always @(posedge clk) begin
        if (reset) begin
            count <= 4'b0000;
        end else if (up_down) begin
            if (count == 4'b1001)
                count <= 4'b0000;
            else
                count <= count + 1;
        end else begin
            if (count == 4'b0000)
                count <= 4'b1001;
            else
                count <= count - 1;
        end
    end
endmodule

bcd/bcd_up_and_down_counter_tb.v
`timescale 1ns / 1ps
module testbranch;
wire [3:0] c;
reg clk, r, u_d;

bcd b1(.count(c), .clk(clk), .reset(r), .up_down(u_d));

always #5 clk = ~clk;

initial begin
   clk = 0;
   r = 1;
   u_d = 1;
   #10;
   r = 0;
   #100;
   u_d = 0;
   #100;
   r = 1;
   #10;
   r = 0;
   $finish;
end

initial begin
   $display("Time\tclk\trst\tup_down\tcount");
   $monitor("%g\t%b\t%b\t%b\t%b", $time, clk, r, u_d, c);
end
initial begin
    $dumpfile("bcd_counter.vcd");    // VCD file name
    $dumpvars(0, testbranch);        // 'testbranch' is your testbench module name
end
endmodule

bcd/bcd_counter.vcd
$date
	Fri Jun 06 01:06:31 2025
$end
$version
	Icarus Verilog
$end
$timescale
	1ps
$end
$scope module testbranch $end
$var wire 4 ! c [3:0] $end
$var reg 1 " clk $end
$var reg 1 # r $end
$var reg 1 $ u_d $end
$scope module b1 $end
$var wire 1 % clk $end
$var wire 1 & reset $end
$var wire 1 ' up_down $end
$var reg 4 ( count [3:0] $end
$upscope $end
$upscope $end
$enddefinitions $end
#0
$dumpvars
bx (
1'
1&
0%
1$
1#
0"
bx !
$end
#5000
b0 (
b0 !
1"
1%
#10000
0"
0%
0#
0&
#15000
b1 (
b1 !
1"
1%
#20000
0"
0%
#25000
b10 (
b10 !
1"
1%
#30000
0"
0%
#35000
b11 (
b11 !
1"
1%
#40000
0"
0%
#45000
b100 (
b100 !
1"
1%
#50000
0"
0%
#55000
b101 (
b101 !
1"
1%
#60000
0"
0%
#65000
b110 (
b110 !
1"
1%
#70000
0"
0%
#75000
b111 (
b111 !
1"
1%
#80000
0"
0%
#85000
b1000 (
b1000 !
1"
1%
#90000
0"
0%
#95000
b1001 (
b1001 !
1"
1%
#100000
0"
0%
#105000
b0 (
b0 !
1"
1%
#110000
0"
0%
0$
0'
#115000
b1001 (
b1001 !
1"
1%
#120000
0"
0%
#125000
b1000 (
b1000 !
1"
1%
#130000
0"
0%
#135000
b111 (
b111 !
1"
1%
#140000
0"
0%
#145000
b110 (
b110 !
1"
1%
#150000
0"
0%
#155000
b101 (
b101 !
1"
1%
#160000
0"
0%
#165000
b100 (
b100 !
1"
1%
#170000
0"
0%
#175000
b11 (
b11 !
1"
1%
#180000
0"
0%
#185000
b10 (
b10 !
1"
1%
#190000
0"
0%
#195000
b1 (
b1 !
1"
1%
#200000
0"
0%
#205000
b0 (
b0 !
1"
1%
#210000
0"
0%
1#
1&
#215000
1"
1%
#220000
0"
0%
0#
0&
